{
  "best_global_step": null,
  "best_metric": null,
  "best_model_checkpoint": null,
  "epoch": 4.424778761061947,
  "eval_steps": 500,
  "global_step": 1000,
  "is_hyper_param_search": false,
  "is_local_process_zero": true,
  "is_world_process_zero": true,
  "log_history": [
    {
      "epoch": 0.04424778761061947,
      "grad_norm": 0.4959162175655365,
      "learning_rate": 4.9601769911504425e-05,
      "loss": 0.9616,
      "step": 10
    },
    {
      "epoch": 0.08849557522123894,
      "grad_norm": 0.543706476688385,
      "learning_rate": 4.915929203539823e-05,
      "loss": 0.1789,
      "step": 20
    },
    {
      "epoch": 0.13274336283185842,
      "grad_norm": 0.18764658272266388,
      "learning_rate": 4.871681415929204e-05,
      "loss": 0.1756,
      "step": 30
    },
    {
      "epoch": 0.17699115044247787,
      "grad_norm": 0.19875116646289825,
      "learning_rate": 4.827433628318585e-05,
      "loss": 0.1211,
      "step": 40
    },
    {
      "epoch": 0.22123893805309736,
      "grad_norm": 0.4372978210449219,
      "learning_rate": 4.783185840707965e-05,
      "loss": 0.1494,
      "step": 50
    },
    {
      "epoch": 0.26548672566371684,
      "grad_norm": 0.8033170700073242,
      "learning_rate": 4.7389380530973454e-05,
      "loss": 0.0961,
      "step": 60
    },
    {
      "epoch": 0.30973451327433627,
      "grad_norm": 0.47448885440826416,
      "learning_rate": 4.694690265486726e-05,
      "loss": 0.0718,
      "step": 70
    },
    {
      "epoch": 0.35398230088495575,
      "grad_norm": 0.6017481088638306,
      "learning_rate": 4.650442477876106e-05,
      "loss": 0.0708,
      "step": 80
    },
    {
      "epoch": 0.39823008849557523,
      "grad_norm": 1.410559892654419,
      "learning_rate": 4.606194690265487e-05,
      "loss": 0.0751,
      "step": 90
    },
    {
      "epoch": 0.4424778761061947,
      "grad_norm": 0.5216594338417053,
      "learning_rate": 4.561946902654867e-05,
      "loss": 0.0632,
      "step": 100
    },
    {
      "epoch": 0.48672566371681414,
      "grad_norm": 1.3156981468200684,
      "learning_rate": 4.5176991150442484e-05,
      "loss": 0.0797,
      "step": 110
    },
    {
      "epoch": 0.5309734513274337,
      "grad_norm": 0.7385573983192444,
      "learning_rate": 4.4734513274336284e-05,
      "loss": 0.0812,
      "step": 120
    },
    {
      "epoch": 0.5752212389380531,
      "grad_norm": 0.9777747988700867,
      "learning_rate": 4.429203539823009e-05,
      "loss": 0.0647,
      "step": 130
    },
    {
      "epoch": 0.6194690265486725,
      "grad_norm": 1.1430387496948242,
      "learning_rate": 4.38495575221239e-05,
      "loss": 0.0702,
      "step": 140
    },
    {
      "epoch": 0.6637168141592921,
      "grad_norm": 1.2549412250518799,
      "learning_rate": 4.34070796460177e-05,
      "loss": 0.0626,
      "step": 150
    },
    {
      "epoch": 0.7079646017699115,
      "grad_norm": 1.3252450227737427,
      "learning_rate": 4.296460176991151e-05,
      "loss": 0.0715,
      "step": 160
    },
    {
      "epoch": 0.7522123893805309,
      "grad_norm": 1.303557276725769,
      "learning_rate": 4.252212389380531e-05,
      "loss": 0.0683,
      "step": 170
    },
    {
      "epoch": 0.7964601769911505,
      "grad_norm": 0.6013315916061401,
      "learning_rate": 4.2079646017699115e-05,
      "loss": 0.0465,
      "step": 180
    },
    {
      "epoch": 0.8407079646017699,
      "grad_norm": 0.40571609139442444,
      "learning_rate": 4.163716814159292e-05,
      "loss": 0.0464,
      "step": 190
    },
    {
      "epoch": 0.8849557522123894,
      "grad_norm": 0.7001799941062927,
      "learning_rate": 4.119469026548673e-05,
      "loss": 0.0421,
      "step": 200
    },
    {
      "epoch": 0.9292035398230089,
      "grad_norm": 0.42837777733802795,
      "learning_rate": 4.0752212389380536e-05,
      "loss": 0.028,
      "step": 210
    },
    {
      "epoch": 0.9734513274336283,
      "grad_norm": 0.6724024415016174,
      "learning_rate": 4.030973451327434e-05,
      "loss": 0.0361,
      "step": 220
    },
    {
      "epoch": 1.0176991150442478,
      "grad_norm": 0.609707772731781,
      "learning_rate": 3.9867256637168144e-05,
      "loss": 0.0748,
      "step": 230
    },
    {
      "epoch": 1.0619469026548674,
      "grad_norm": 0.4542962312698364,
      "learning_rate": 3.9424778761061945e-05,
      "loss": 0.0541,
      "step": 240
    },
    {
      "epoch": 1.1061946902654867,
      "grad_norm": 0.8564791679382324,
      "learning_rate": 3.898230088495575e-05,
      "loss": 0.0329,
      "step": 250
    },
    {
      "epoch": 1.1504424778761062,
      "grad_norm": 0.7789502143859863,
      "learning_rate": 3.853982300884956e-05,
      "loss": 0.0313,
      "step": 260
    },
    {
      "epoch": 1.1946902654867257,
      "grad_norm": 0.42777928709983826,
      "learning_rate": 3.8097345132743366e-05,
      "loss": 0.0379,
      "step": 270
    },
    {
      "epoch": 1.238938053097345,
      "grad_norm": 0.5324400663375854,
      "learning_rate": 3.7654867256637174e-05,
      "loss": 0.0323,
      "step": 280
    },
    {
      "epoch": 1.2831858407079646,
      "grad_norm": 0.17031843960285187,
      "learning_rate": 3.7212389380530974e-05,
      "loss": 0.0264,
      "step": 290
    },
    {
      "epoch": 1.3274336283185841,
      "grad_norm": 0.8019858002662659,
      "learning_rate": 3.676991150442478e-05,
      "loss": 0.0344,
      "step": 300
    },
    {
      "epoch": 1.3716814159292037,
      "grad_norm": 0.45179447531700134,
      "learning_rate": 3.632743362831859e-05,
      "loss": 0.0225,
      "step": 310
    },
    {
      "epoch": 1.415929203539823,
      "grad_norm": 0.4724556803703308,
      "learning_rate": 3.588495575221239e-05,
      "loss": 0.0266,
      "step": 320
    },
    {
      "epoch": 1.4601769911504425,
      "grad_norm": 1.6522433757781982,
      "learning_rate": 3.5442477876106196e-05,
      "loss": 0.0345,
      "step": 330
    },
    {
      "epoch": 1.504424778761062,
      "grad_norm": 0.8695636987686157,
      "learning_rate": 3.5e-05,
      "loss": 0.0292,
      "step": 340
    },
    {
      "epoch": 1.5486725663716814,
      "grad_norm": 0.8293254971504211,
      "learning_rate": 3.455752212389381e-05,
      "loss": 0.0284,
      "step": 350
    },
    {
      "epoch": 1.592920353982301,
      "grad_norm": 0.4034616947174072,
      "learning_rate": 3.411504424778761e-05,
      "loss": 0.0304,
      "step": 360
    },
    {
      "epoch": 1.6371681415929205,
      "grad_norm": 0.3311833441257477,
      "learning_rate": 3.367256637168142e-05,
      "loss": 0.0338,
      "step": 370
    },
    {
      "epoch": 1.6814159292035398,
      "grad_norm": 0.30634060502052307,
      "learning_rate": 3.3230088495575226e-05,
      "loss": 0.0195,
      "step": 380
    },
    {
      "epoch": 1.7256637168141593,
      "grad_norm": 1.2402479648590088,
      "learning_rate": 3.2787610619469026e-05,
      "loss": 0.035,
      "step": 390
    },
    {
      "epoch": 1.7699115044247788,
      "grad_norm": 1.4481678009033203,
      "learning_rate": 3.2345132743362834e-05,
      "loss": 0.0295,
      "step": 400
    },
    {
      "epoch": 1.8141592920353982,
      "grad_norm": 0.4063177704811096,
      "learning_rate": 3.1902654867256634e-05,
      "loss": 0.0226,
      "step": 410
    },
    {
      "epoch": 1.8584070796460177,
      "grad_norm": 0.1921851933002472,
      "learning_rate": 3.146017699115044e-05,
      "loss": 0.0335,
      "step": 420
    },
    {
      "epoch": 1.9026548672566372,
      "grad_norm": 0.9045236706733704,
      "learning_rate": 3.101769911504425e-05,
      "loss": 0.0266,
      "step": 430
    },
    {
      "epoch": 1.9469026548672566,
      "grad_norm": 0.7027932405471802,
      "learning_rate": 3.0575221238938056e-05,
      "loss": 0.0193,
      "step": 440
    },
    {
      "epoch": 1.991150442477876,
      "grad_norm": 2.9368507862091064,
      "learning_rate": 3.013274336283186e-05,
      "loss": 0.041,
      "step": 450
    },
    {
      "epoch": 2.0353982300884956,
      "grad_norm": 0.23607750236988068,
      "learning_rate": 2.9690265486725667e-05,
      "loss": 0.0078,
      "step": 460
    },
    {
      "epoch": 2.079646017699115,
      "grad_norm": 0.8680390119552612,
      "learning_rate": 2.924778761061947e-05,
      "loss": 0.0161,
      "step": 470
    },
    {
      "epoch": 2.1238938053097347,
      "grad_norm": 0.6745836138725281,
      "learning_rate": 2.8805309734513275e-05,
      "loss": 0.0123,
      "step": 480
    },
    {
      "epoch": 2.168141592920354,
      "grad_norm": 0.25793886184692383,
      "learning_rate": 2.836283185840708e-05,
      "loss": 0.0106,
      "step": 490
    },
    {
      "epoch": 2.2123893805309733,
      "grad_norm": 0.6405306458473206,
      "learning_rate": 2.7920353982300883e-05,
      "loss": 0.0107,
      "step": 500
    },
    {
      "epoch": 2.256637168141593,
      "grad_norm": 0.33836641907691956,
      "learning_rate": 2.7477876106194693e-05,
      "loss": 0.0106,
      "step": 510
    },
    {
      "epoch": 2.3008849557522124,
      "grad_norm": 1.1658111810684204,
      "learning_rate": 2.7035398230088497e-05,
      "loss": 0.0172,
      "step": 520
    },
    {
      "epoch": 2.3451327433628317,
      "grad_norm": 0.45806869864463806,
      "learning_rate": 2.6592920353982305e-05,
      "loss": 0.0121,
      "step": 530
    },
    {
      "epoch": 2.3893805309734515,
      "grad_norm": 0.5129255652427673,
      "learning_rate": 2.615044247787611e-05,
      "loss": 0.0088,
      "step": 540
    },
    {
      "epoch": 2.433628318584071,
      "grad_norm": 0.4126395583152771,
      "learning_rate": 2.5707964601769912e-05,
      "loss": 0.0135,
      "step": 550
    },
    {
      "epoch": 2.47787610619469,
      "grad_norm": 0.3089286684989929,
      "learning_rate": 2.5265486725663716e-05,
      "loss": 0.0095,
      "step": 560
    },
    {
      "epoch": 2.52212389380531,
      "grad_norm": 0.28961512446403503,
      "learning_rate": 2.4823008849557523e-05,
      "loss": 0.0113,
      "step": 570
    },
    {
      "epoch": 2.566371681415929,
      "grad_norm": 0.06943120062351227,
      "learning_rate": 2.438053097345133e-05,
      "loss": 0.0057,
      "step": 580
    },
    {
      "epoch": 2.6106194690265485,
      "grad_norm": 0.22752171754837036,
      "learning_rate": 2.3938053097345135e-05,
      "loss": 0.0089,
      "step": 590
    },
    {
      "epoch": 2.6548672566371683,
      "grad_norm": 1.7488666772842407,
      "learning_rate": 2.349557522123894e-05,
      "loss": 0.0161,
      "step": 600
    },
    {
      "epoch": 2.6991150442477876,
      "grad_norm": 0.028878159821033478,
      "learning_rate": 2.3053097345132742e-05,
      "loss": 0.0101,
      "step": 610
    },
    {
      "epoch": 2.7433628318584073,
      "grad_norm": 0.3271908462047577,
      "learning_rate": 2.261061946902655e-05,
      "loss": 0.0126,
      "step": 620
    },
    {
      "epoch": 2.7876106194690267,
      "grad_norm": 0.29413530230522156,
      "learning_rate": 2.2168141592920353e-05,
      "loss": 0.0117,
      "step": 630
    },
    {
      "epoch": 2.831858407079646,
      "grad_norm": 0.3529909551143646,
      "learning_rate": 2.172566371681416e-05,
      "loss": 0.0148,
      "step": 640
    },
    {
      "epoch": 2.8761061946902657,
      "grad_norm": 0.75042325258255,
      "learning_rate": 2.1283185840707965e-05,
      "loss": 0.0131,
      "step": 650
    },
    {
      "epoch": 2.920353982300885,
      "grad_norm": 0.11193757504224777,
      "learning_rate": 2.0840707964601772e-05,
      "loss": 0.0099,
      "step": 660
    },
    {
      "epoch": 2.9646017699115044,
      "grad_norm": 0.13854844868183136,
      "learning_rate": 2.0398230088495576e-05,
      "loss": 0.0143,
      "step": 670
    },
    {
      "epoch": 3.0088495575221237,
      "grad_norm": 0.2109891027212143,
      "learning_rate": 1.995575221238938e-05,
      "loss": 0.0126,
      "step": 680
    },
    {
      "epoch": 3.0530973451327434,
      "grad_norm": 0.11801661550998688,
      "learning_rate": 1.9513274336283187e-05,
      "loss": 0.0042,
      "step": 690
    },
    {
      "epoch": 3.0973451327433628,
      "grad_norm": 0.03905235230922699,
      "learning_rate": 1.9070796460176994e-05,
      "loss": 0.0047,
      "step": 700
    },
    {
      "epoch": 3.1415929203539825,
      "grad_norm": 0.35300305485725403,
      "learning_rate": 1.8628318584070798e-05,
      "loss": 0.006,
      "step": 710
    },
    {
      "epoch": 3.185840707964602,
      "grad_norm": 0.3082393407821655,
      "learning_rate": 1.8185840707964602e-05,
      "loss": 0.0048,
      "step": 720
    },
    {
      "epoch": 3.230088495575221,
      "grad_norm": 0.2692353129386902,
      "learning_rate": 1.7743362831858406e-05,
      "loss": 0.0041,
      "step": 730
    },
    {
      "epoch": 3.274336283185841,
      "grad_norm": 0.2280052900314331,
      "learning_rate": 1.7300884955752213e-05,
      "loss": 0.0064,
      "step": 740
    },
    {
      "epoch": 3.3185840707964602,
      "grad_norm": 0.4605625867843628,
      "learning_rate": 1.6858407079646017e-05,
      "loss": 0.0052,
      "step": 750
    },
    {
      "epoch": 3.3628318584070795,
      "grad_norm": 0.5817924737930298,
      "learning_rate": 1.6415929203539824e-05,
      "loss": 0.0054,
      "step": 760
    },
    {
      "epoch": 3.4070796460176993,
      "grad_norm": 0.1144564300775528,
      "learning_rate": 1.5973451327433628e-05,
      "loss": 0.0078,
      "step": 770
    },
    {
      "epoch": 3.4513274336283186,
      "grad_norm": 0.3505806624889374,
      "learning_rate": 1.5530973451327435e-05,
      "loss": 0.0035,
      "step": 780
    },
    {
      "epoch": 3.495575221238938,
      "grad_norm": 0.16440589725971222,
      "learning_rate": 1.508849557522124e-05,
      "loss": 0.0039,
      "step": 790
    },
    {
      "epoch": 3.5398230088495577,
      "grad_norm": 0.05056627467274666,
      "learning_rate": 1.4646017699115045e-05,
      "loss": 0.0015,
      "step": 800
    },
    {
      "epoch": 3.584070796460177,
      "grad_norm": 0.3948097825050354,
      "learning_rate": 1.4203539823008849e-05,
      "loss": 0.0112,
      "step": 810
    },
    {
      "epoch": 3.6283185840707963,
      "grad_norm": 0.4897669851779938,
      "learning_rate": 1.3761061946902656e-05,
      "loss": 0.0122,
      "step": 820
    },
    {
      "epoch": 3.672566371681416,
      "grad_norm": 0.2935830354690552,
      "learning_rate": 1.3318584070796462e-05,
      "loss": 0.0036,
      "step": 830
    },
    {
      "epoch": 3.7168141592920354,
      "grad_norm": 0.2394050657749176,
      "learning_rate": 1.2876106194690265e-05,
      "loss": 0.0043,
      "step": 840
    },
    {
      "epoch": 3.7610619469026547,
      "grad_norm": 0.44242650270462036,
      "learning_rate": 1.2433628318584071e-05,
      "loss": 0.007,
      "step": 850
    },
    {
      "epoch": 3.8053097345132745,
      "grad_norm": 0.017305785790085793,
      "learning_rate": 1.1991150442477877e-05,
      "loss": 0.0082,
      "step": 860
    },
    {
      "epoch": 3.849557522123894,
      "grad_norm": 0.18204471468925476,
      "learning_rate": 1.1548672566371682e-05,
      "loss": 0.0021,
      "step": 870
    },
    {
      "epoch": 3.893805309734513,
      "grad_norm": 0.2622729539871216,
      "learning_rate": 1.1106194690265486e-05,
      "loss": 0.0052,
      "step": 880
    },
    {
      "epoch": 3.938053097345133,
      "grad_norm": 0.005774308927357197,
      "learning_rate": 1.0663716814159293e-05,
      "loss": 0.01,
      "step": 890
    },
    {
      "epoch": 3.982300884955752,
      "grad_norm": 0.011851790361106396,
      "learning_rate": 1.0221238938053097e-05,
      "loss": 0.0032,
      "step": 900
    },
    {
      "epoch": 4.0265486725663715,
      "grad_norm": 0.2588390111923218,
      "learning_rate": 9.778761061946903e-06,
      "loss": 0.0029,
      "step": 910
    },
    {
      "epoch": 4.070796460176991,
      "grad_norm": 0.7789587378501892,
      "learning_rate": 9.336283185840708e-06,
      "loss": 0.0088,
      "step": 920
    },
    {
      "epoch": 4.115044247787611,
      "grad_norm": 0.5222839117050171,
      "learning_rate": 8.893805309734514e-06,
      "loss": 0.0014,
      "step": 930
    },
    {
      "epoch": 4.15929203539823,
      "grad_norm": 0.10554508864879608,
      "learning_rate": 8.451327433628318e-06,
      "loss": 0.0039,
      "step": 940
    },
    {
      "epoch": 4.20353982300885,
      "grad_norm": 0.019039666280150414,
      "learning_rate": 8.008849557522125e-06,
      "loss": 0.004,
      "step": 950
    },
    {
      "epoch": 4.247787610619469,
      "grad_norm": 0.01414848119020462,
      "learning_rate": 7.566371681415929e-06,
      "loss": 0.0026,
      "step": 960
    },
    {
      "epoch": 4.292035398230088,
      "grad_norm": 0.042329829186201096,
      "learning_rate": 7.123893805309735e-06,
      "loss": 0.0019,
      "step": 970
    },
    {
      "epoch": 4.336283185840708,
      "grad_norm": 0.2617729604244232,
      "learning_rate": 6.68141592920354e-06,
      "loss": 0.0021,
      "step": 980
    },
    {
      "epoch": 4.380530973451328,
      "grad_norm": 0.05003836378455162,
      "learning_rate": 6.238938053097346e-06,
      "loss": 0.005,
      "step": 990
    },
    {
      "epoch": 4.424778761061947,
      "grad_norm": 0.22930768132209778,
      "learning_rate": 5.796460176991151e-06,
      "loss": 0.0036,
      "step": 1000
    }
  ],
  "logging_steps": 10,
  "max_steps": 1130,
  "num_input_tokens_seen": 0,
  "num_train_epochs": 5,
  "save_steps": 500,
  "stateful_callbacks": {
    "TrainerControl": {
      "args": {
        "should_epoch_stop": false,
        "should_evaluate": false,
        "should_log": false,
        "should_save": true,
        "should_training_stop": false
      },
      "attributes": {}
    }
  },
  "total_flos": 521119931916288.0,
  "train_batch_size": 16,
  "trial_name": null,
  "trial_params": null
}
